folder/__init__.py
testfilebyustopythoncoolgoat-0.0.2.dist-info/METADATA
testfilebyustopythoncoolgoat-0.0.2.dist-info/WHEEL
testfilebyustopythoncoolgoat-0.0.2.dist-info/top_level.txt
testfilebyustopythoncoolgoat-0.0.2.dist-info/RECORD
